docklib/__init__.py
docklib/docklib.py
docklib-2.0.0.dist-info/LICENSE.md
docklib-2.0.0.dist-info/METADATA
docklib-2.0.0.dist-info/WHEEL
docklib-2.0.0.dist-info/top_level.txt
docklib-2.0.0.dist-info/RECORD
