Metadata-Version: 2.1
Name: docklib
Version: 2.0.0
Summary: Python module intended to assist IT administrators with manipulation of the macOS Dock.
Home-page: https://github.com/homebysix/docklib
Author: Elliot Jordan
Author-email: elliot@elliotjordan.com
License: Apache 2.0
Classifier: Development Status :: 5 - Production/Stable
Classifier: Environment :: MacOS X
Classifier: Intended Audience :: Information Technology
Classifier: Intended Audience :: System Administrators
Classifier: License :: OSI Approved :: Apache Software License
Classifier: Programming Language :: Python :: 2
Classifier: Programming Language :: Python :: 3
Classifier: Topic :: System :: Systems Administration
Classifier: Topic :: Utilities
License-File: LICENSE.md
